Single_Cycle_Top.v
module PC_Module(clk,rst,PC,PC_Next);
    input clk,rst;
    input [31:0]PC_Next;
    output [31:0]PC;
    reg [31:0]PC;

    always @(posedge clk)
    begin
        if(~rst)
            PC <= {32{1'b0}};
        else
            PC <= PC_Next;
    end
endmodule

module Instruction_Memory(rst,A,RD);

  input rst;
  input [31:0]A;
  output [31:0]RD;

  reg [31:0] mem [1023:0];
  
  assign RD = (~rst) ? {32{1'b0}} : mem[A[31:2]];

  initial begin
    $readmemh("memfile.hex",mem);
  end


endmodule

module Register_File(clk,rst,WE3,WD3,A1,A2,A3,RD1,RD2);

    input clk,rst,WE3;
    input [4:0]A1,A2,A3;
    input [31:0]WD3;
    output [31:0]RD1,RD2;

    reg [31:0] Register [31:0];

    always @ (posedge clk)
    begin
        if(WE3)
            Register[A3] <= WD3;
    end

    assign RD1 = (~rst) ? 32'd0 : Register[A1];
    assign RD2 = (~rst) ? 32'd0 : Register[A2];

    initial begin
        Register[0] = 32'h00000000;         
        Register[2] = 32'h00000014;
    end

endmodule

module Sign_Extend (In,Imm_Ext,ImmSrc);

    input [31:0]In;
    input [1:0] ImmSrc;
    output [31:0]Imm_Ext;

    assign Imm_Ext = (ImmSrc == 2'b00) ? ({{20{In[31]}}, In[31:20]}):
                     (ImmSrc == 2'b01) ? ({{20{In[31]}}, In[31:25], In[11:7]} ):
                     (ImmSrc == 2'b10) ? ({{20{In[31]}}, In[7], In[30:25], In[11:8], 1'b0}):
                                         {{12{In[31]}}, In[19:12], In[20], In[30:21], 1'b0};
                                
endmodule

module ALU(A,B,Result,ALUControl,OverFlow,Carry,Zero,Negative);

    input [31:0]A,B;
    input [2:0]ALUControl;
    output Carry,OverFlow,Zero,Negative;
    output [31:0]Result;

    wire Cout;
    wire [31:0]Sum;

    assign {Cout,Sum} = (ALUControl[0] == 1'b0) ? A + B :
                                          (A + ((~B)+1)) ;
    assign Result = (ALUControl == 3'b000) ? Sum :
                    (ALUControl == 3'b001) ? Sum :
                    (ALUControl == 3'b010) ? A & B :
                    (ALUControl == 3'b011) ? A | B :
                    (ALUControl == 3'b101) ? {{31{1'b0}},(Sum[31])} : {32{1'b0}};
    
    assign OverFlow = ((Sum[31] ^ A[31]) & 
                      (~(ALUControl[0] ^ B[31] ^ A[31])) &
                      (~ALUControl[1]));
    assign Carry = ((~ALUControl[1]) & Cout);
    assign Zero = &(~Result);
    assign Negative = Result[31];

endmodule

module ALU_Decoder(ALUOp,funct3,funct7,op,ALUControl);

    input [1:0]ALUOp;
    input [2:0]funct3;
    input [6:0]funct7,op;
    output [2:0]ALUControl;
    
    assign ALUControl = (ALUOp == 2'b00) ? 3'b000 :
                        (ALUOp == 2'b01) ? 3'b001 :
                        ((ALUOp == 2'b10) & (funct3 == 3'b000) & ({op[5],funct7[5]} == 2'b11)) ? 3'b001 : 
                        ((ALUOp == 2'b10) & (funct3 == 3'b000) & ({op[5],funct7[5]} != 2'b11)) ? 3'b000 : 
                        ((ALUOp == 2'b10) & (funct3 == 3'b010)) ? 3'b101 : 
                        ((ALUOp == 2'b10) & (funct3 == 3'b110)) ? 3'b011 : 
                        ((ALUOp == 2'b10) & (funct3 == 3'b111)) ? 3'b010 : 
                                                                  3'b000 ;
endmodule

module Main_Decoder(Op,RegWrite,ImmSrc,ALUSrc,MemWrite,ResultSrc,Branch,ALUOp,jump);
    input [6:0]Op;
    output RegWrite,ALUSrc,MemWrite,Branch,jump;
    output [1:0]ImmSrc,ResultSrc,ALUOp;

    assign RegWrite = (Op == 7'b0000011 | Op == 7'b0110011 | Op == 7'b0010011 | Op == 7'b1101111 ) ? 1'b1 :
                                                              1'b0 ;
    assign ImmSrc = (Op == 7'b0100011) ? 2'b01 : 
                    (Op == 7'b1100011) ? 2'b10 : 
                    (Op == 7'b1101111) ? 2'b11 :   
                                         2'b00 ;
    assign ALUSrc = (Op == 7'b0110011 | Op == 7'b1100011) ? 1'b0 :
                                                            1'b1 ;
    assign MemWrite = (Op == 7'b0100011) ? 1'b1 :
                                           1'b0 ;
    assign ResultSrc = (Op == 7'b0000011) ? 2'b01 :
                         (Op == 7'b1101111) ? 2'b10 :
                                            2'b00 ;
    assign Branch = (Op == 7'b1100011) ? 1'b1 :
                                         1'b0 ;
    assign ALUOp = (Op == 7'b0110011 | Op == 7'b0010011) ? 2'b10 :
                   (Op == 7'b1100011) ? 2'b01 :
                                        2'b00 ;
    assign jump = (Op == 7'b1101111) ? 1'b1:
                                       1'b0;

endmodule

module Control_Unit_Top(Op,pcSRC,RegWrite,ImmSrc,ALUSrc,MemWrite,ResultSrc,funct3,funct7,zero,ALUControl);

    input [6:0]Op,funct7;
    input [2:0]funct3;
    input zero;
    wire Branch,jump;
    output RegWrite,ALUSrc,MemWrite,pcSRC;
    output [1:0]ImmSrc,ResultSrc;
    output [2:0]ALUControl;

    wire [1:0]ALUOp;

    Main_Decoder Main_Decoder(
                .Op(Op),
                .RegWrite(RegWrite),
                .ImmSrc(ImmSrc),
                .MemWrite(MemWrite),
                .ResultSrc(ResultSrc),
                .Branch(Branch),
                .ALUSrc(ALUSrc),
                .ALUOp(ALUOp),
                .jump(jump)
    );

    assign pcSRC= (Branch & zero) | jump;

    ALU_Decoder ALU_Decoder(
                            .ALUOp(ALUOp),
                            .funct3(funct3),
                            .funct7(funct7),
                            .op(Op),
                            .ALUControl(ALUControl)
    );


endmodule

module Data_Memory(clk,rst,WE,WD,A,RD);

    input clk,rst,WE;
    input [31:0]A,WD;
    output [31:0]RD;

    reg [31:0] mem [1023:0];

    always @ (posedge clk)
    begin
        if(WE)
            mem[A] <= WD;
    end

    assign RD = (~rst) ? 32'd0 : mem[A];

    initial begin
        mem[0] = 32'h00000003; //3
        mem[1] = 32'h00000007; //7
        mem[2] = 32'h00000002; //2
        mem[3] = 32'h00000006; //6
        mem[4] = 32'h00000005; //5
        mem[5] = 32'h00000004; //4
        mem[6] = 32'h00000001; //1
        mem[7] = 32'h000003e8; //1000
        mem[8] = 32'h000003e7; //999
        mem[9] = 32'h00000019; //25
        mem[10] = 32'h0000005a; //90
        mem[11] = 32'h00000064; //100   
        mem[12] = 32'h0000001e; //30
        mem[13] = 32'h00000014; //20
        mem[14] = 32'h0000000A; //10
        mem[15] = 32'h000000c8; //200
        mem[16] = 32'h00000ce4; //3300
        mem[17] = 32'h000000fa; //250
        mem[18] = 32'h0000000c; //12
        mem[19] = 32'h0000004b; //75
        /*---------------------------------------------------------------------------------------------------------------*/
        mem[20] = 32'h00000011; //17
        mem[21] = 32'h0000000d; //13
        mem[22] = 32'h00000012; //18
        mem[23] = 32'h0000000e; //14
        mem[24] = 32'h0000000f; //15
        mem[25] = 32'h00000010; //16
        mem[26] = 32'h00000013; //19
        mem[27] = 32'h00000001; //1
        mem[28] = 32'h00000002; //2
        mem[29] = 32'h00000009; //9
        mem[30] = 32'h00000006; //6
        mem[31] = 32'h00000005; //5
        mem[32] = 32'h00000008; //8
        mem[33] = 32'h0000000a; //10
        mem[34] = 32'h0000000c; //12
        mem[35] = 32'h00000004; //4
        mem[36] = 32'h00000000; //0
        mem[37] = 32'h00000003; //3
        mem[38] = 32'h0000000b; //11
        mem[39] = 32'h00000007; //7
    end


endmodule

module PC_Adder (a,b,c);

    input [31:0]a,b;
    output [31:0]c;

    assign c = a + b;
    
endmodule

module Mux (a,b,s,c);

    input [31:0]a,b;
    input s;
    output [31:0]c;

    assign c = (~s) ? a : b ;
    
endmodule

module Mux4 (a,b,d,f,s,c);

    input [31:0]a,b,d,f;
    input [1:0]s;
    output [31:0]c;
    
    assign c = (s==2'b00) ? a :
               (s==2'b01) ? b:
                (s==2'b10) ? d :
                f;
    
endmodule


module Single_Cycle_Top(clk,rst);

    input clk,rst;

    wire [31:0] PC_Top,RD_Instr,RD1_Top,Imm_Ext_Top,ALUResult,ReadData,PCPlus4,RD2_Top,SrcB,Result,pcTarget,PC_Next;
    wire RegWrite,MemWrite,ALUSrc,pcSRC;
    wire [1:0]ImmSrc , ResultSrc;
    wire [2:0]ALUControl_Top; 

    Mux Mux_pcSRC(
        .a(PCPlus4),
        .b(pcTarget),
        .s(pcSRC),
        .c(PC_Next)
    );

    PC_Module PC(
        .clk(clk),
        .rst(rst),
        .PC(PC_Top),
        .PC_Next(PC_Next)
    );

    PC_Adder PC_Adder(
                    .a(PC_Top),
                    .b(32'd4),
                    .c(PCPlus4)
    );

    PC_Adder adder_pcTarget(
        .a(PC_Top),
        .b(Imm_Ext_Top),
        .c(pcTarget)
    );
    
    Instruction_Memory Instruction_Memory(
                            .rst(rst),
                            .A(PC_Top),
                            .RD(RD_Instr)
    );

    Register_File Register_File(
                            .clk(clk),
                            .rst(rst),
                            .WE3(RegWrite),
                            .WD3(Result),
                            .A1(RD_Instr[19:15]),
                            .A2(RD_Instr[24:20]),
                            .A3(RD_Instr[11:7]),
                            .RD1(RD1_Top),
                            .RD2(RD2_Top)
    );

    Sign_Extend Sign_Extend(
                        .In(RD_Instr),
                        .ImmSrc(ImmSrc),
                        .Imm_Ext(Imm_Ext_Top)
    );

    Mux Mux_Register_to_ALU(
                            .a(RD2_Top),
                            .b(Imm_Ext_Top),
                            .s(ALUSrc),
                            .c(SrcB)
    );

    ALU ALU(
            .A(RD1_Top),
            .B(SrcB),
            .Result(ALUResult),
            .ALUControl(ALUControl_Top),
            .OverFlow(),
            .Carry(),
            .Zero(zero),
            .Negative()
    );

    Control_Unit_Top Control_Unit_Top(
                            .Op(RD_Instr[6:0]),
                            .RegWrite(RegWrite),
                            .ImmSrc(ImmSrc),
                            .ALUSrc(ALUSrc),
                            .MemWrite(MemWrite),
                            .pcSRC(pcSRC),
                            .ResultSrc(ResultSrc),
                            .zero(zero),
                            .funct3(RD_Instr[14:12]),
                            .funct7(RD_Instr[31:25]),
                            .ALUControl(ALUControl_Top)
    );

    Data_Memory Data_Memory(
                        .clk(clk),
                        .rst(rst),
                        .WE(MemWrite),
                        .WD(RD2_Top),
                        .A(ALUResult),
                        .RD(ReadData)
    );

    Mux4 Mux_DataMemory_to_Register(
                            .a(ALUResult),
                            .b(ReadData),
                            .d(PCPlus4),
                            .f(),
                            .s(ResultSrc),
                            .c(Result)
    );

endmodule

//iverilog -o single_cycle_top_tb.vvp single_cycle_top_tb.v
//vvp single_cycle_top_tb.vvp
//gtkwave single_cycle_top_tb.vcd

Single_Cycle_Top_Tb.v
`include "Single_Cycle_Top.v"
module Single_Cycle_Top_Tb ();
    
    reg clk=1'b1,rst;

    Single_Cycle_Top Single_Cycle_Top(
                                .clk(clk),
                                .rst(rst)
    );

    initial begin
        $dumpfile("single_cycle_top_tb.vcd");
        $dumpvars(0);
    end

    always 
    begin
        clk = ~ clk;
        #5;  
        
    end
    
    initial
    begin
        rst <= 1'b0;
        #10;

        rst <=1'b1;
        #10000;
        $finish;
    end
endmodule

single_cycle_top_tb.vcd
$date
	Wed May 15 22:00:57 2024
$end
$version
	Icarus Verilog
$end
$timescale
	1s
$end
$scope module Single_Cycle_Top_Tb $end
$var reg 1 ! clk $end
$var reg 1 " rst $end
$scope module Single_Cycle_Top $end
$var wire 1 ! clk $end
$var wire 1 " rst $end
$var wire 1 # zero $end
$var wire 32 $ pcTarget [31:0] $end
$var wire 1 % pcSRC $end
$var wire 32 & SrcB [31:0] $end
$var wire 2 ' ResultSrc [1:0] $end
$var wire 32 ( Result [31:0] $end
$var wire 1 ) RegWrite $end
$var wire 32 * ReadData [31:0] $end
$var wire 32 + RD_Instr [31:0] $end
$var wire 32 , RD2_Top [31:0] $end
$var wire 32 - RD1_Top [31:0] $end
$var wire 32 . PC_Top [31:0] $end
$var wire 32 / PC_Next [31:0] $end
$var wire 32 0 PCPlus4 [31:0] $end
$var wire 1 1 MemWrite $end
$var wire 32 2 Imm_Ext_Top [31:0] $end
$var wire 2 3 ImmSrc [1:0] $end
$var wire 1 4 ALUSrc $end
$var wire 32 5 ALUResult [31:0] $end
$var wire 3 6 ALUControl_Top [2:0] $end
$scope module ALU $end
$var wire 1 7 Carry $end
$var wire 1 8 OverFlow $end
$var wire 1 # Zero $end
$var wire 32 9 Sum [31:0] $end
$var wire 32 : Result [31:0] $end
$var wire 1 ; Negative $end
$var wire 1 < Cout $end
$var wire 32 = B [31:0] $end
$var wire 3 > ALUControl [2:0] $end
$var wire 32 ? A [31:0] $end
$upscope $end
$scope module Control_Unit_Top $end
$var wire 7 @ Op [6:0] $end
$var wire 3 A funct3 [2:0] $end
$var wire 7 B funct7 [6:0] $end
$var wire 1 % pcSRC $end
$var wire 1 # zero $end
$var wire 1 C jump $end
$var wire 2 D ResultSrc [1:0] $end
$var wire 1 ) RegWrite $end
$var wire 1 1 MemWrite $end
$var wire 2 E ImmSrc [1:0] $end
$var wire 1 F Branch $end
$var wire 1 4 ALUSrc $end
$var wire 2 G ALUOp [1:0] $end
$var wire 3 H ALUControl [2:0] $end
$scope module ALU_Decoder $end
$var wire 3 I funct3 [2:0] $end
$var wire 7 J funct7 [6:0] $end
$var wire 7 K op [6:0] $end
$var wire 2 L ALUOp [1:0] $end
$var wire 3 M ALUControl [2:0] $end
$upscope $end
$scope module Main_Decoder $end
$var wire 7 N Op [6:0] $end
$var wire 1 C jump $end
$var wire 2 O ResultSrc [1:0] $end
$var wire 1 ) RegWrite $end
$var wire 1 1 MemWrite $end
$var wire 2 P ImmSrc [1:0] $end
$var wire 1 F Branch $end
$var wire 1 4 ALUSrc $end
$var wire 2 Q ALUOp [1:0] $end
$upscope $end
$upscope $end
$scope module Data_Memory $end
$var wire 32 R A [31:0] $end
$var wire 1 1 WE $end
$var wire 1 ! clk $end
$var wire 1 " rst $end
$var wire 32 S WD [31:0] $end
$var wire 32 T RD [31:0] $end
$upscope $end
$scope module Instruction_Memory $end
$var wire 1 " rst $end
$var wire 32 U RD [31:0] $end
$var wire 32 V A [31:0] $end
$upscope $end
$scope module Mux_DataMemory_to_Register $end
$var wire 32 W a [31:0] $end
$var wire 32 X b [31:0] $end
$var wire 32 Y f [31:0] $end
$var wire 2 Z s [1:0] $end
$var wire 32 [ d [31:0] $end
$var wire 32 \ c [31:0] $end
$upscope $end
$scope module Mux_Register_to_ALU $end
$var wire 1 4 s $end
$var wire 32 ] c [31:0] $end
$var wire 32 ^ b [31:0] $end
$var wire 32 _ a [31:0] $end
$upscope $end
$scope module Mux_pcSRC $end
$var wire 1 % s $end
$var wire 32 ` c [31:0] $end
$var wire 32 a b [31:0] $end
$var wire 32 b a [31:0] $end
$upscope $end
$scope module PC $end
$var wire 32 c PC_Next [31:0] $end
$var wire 1 ! clk $end
$var wire 1 " rst $end
$var reg 32 d PC [31:0] $end
$upscope $end
$scope module PC_Adder $end
$var wire 32 e a [31:0] $end
$var wire 32 f b [31:0] $end
$var wire 32 g c [31:0] $end
$upscope $end
$scope module Register_File $end
$var wire 5 h A1 [4:0] $end
$var wire 5 i A2 [4:0] $end
$var wire 5 j A3 [4:0] $end
$var wire 32 k WD3 [31:0] $end
$var wire 1 ) WE3 $end
$var wire 1 ! clk $end
$var wire 1 " rst $end
$var wire 32 l RD2 [31:0] $end
$var wire 32 m RD1 [31:0] $end
$upscope $end
$scope module Sign_Extend $end
$var wire 2 n ImmSrc [1:0] $end
$var wire 32 o In [31:0] $end
$var wire 32 p Imm_Ext [31:0] $end
$upscope $end
$scope module adder_pcTarget $end
$var wire 32 q a [31:0] $end
$var wire 32 r b [31:0] $end
$var wire 32 s c [31:0] $end
$upscope $end
$upscope $end
$upscope $end
$enddefinitions $end
$comment Show the parameter values. $end
$dumpall
$end
#0
$dumpvars
bx s
b0 r
bx q
b0 p
b0 o
b0 n
b0 m
b0 l
b0 k
b0 j
b0 i
b0 h
bx g
b100 f
bx e
bx d
bx c
bx b
bx a
bx `
b0 _
b0 ^
b0 ]
b0 \
bx [
b0 Z
bz Y
b0 X
b0 W
bx V
b0 U
b0 T
b0 S
b0 R
b0 Q
b0 P
b0 O
b0 N
b0 M
b0 L
b0 K
b0 J
b0 I
b0 H
b0 G
0F
b0 E
b0 D
0C
b0 B
b0 A
b0 @
b0 ?
b0 >
b0 =
0<
0;
b0 :
b0 9
08
07
b0 6
b0 5
14
b0 3
b0 2
01
bx 0
bx /
bx .
b0 -
b0 ,
b0 +
b0 *
0)
b0 (
b0 '
b0 &
0%
bx $
1#
0"
0!
$end
#5
b100 /
b100 `
b100 c
b100 0
b100 [
b100 b
b100 g
b0 $
b0 a
b0 s
b0 .
b0 V
b0 d
b0 e
b0 q
1!
#10
1;
17
1<
b11111111111111111111111111101100 (
b11111111111111111111111111101100 \
b11111111111111111111111111101100 k
0#
b11111111111111111111111111101100 5
b11111111111111111111111111101100 :
b11111111111111111111111111101100 R
b11111111111111111111111111101100 W
b100 /
b100 `
b100 c
b11111111111111111111111111101100 9
b1 6
b1 >
b1 H
b1 M
0%
b10100 &
b10100 =
b10100 ]
b10 3
b10 E
b10 P
b10 n
04
b1 G
b1 L
b1 Q
b11000 $
b11000 a
b11000 s
b11000 2
b11000 ^
b11000 p
b11000 r
1F
b10100 ,
b10100 S
b10100 _
b10100 l
b1100011 @
b1100011 K
b1100011 N
b11000 j
b10 i
bx *
bx T
bx X
b1000000000110001100011 +
b1000000000110001100011 U
b1000000000110001100011 o
1"
0!
#15
b10001 *
b10001 T
b10001 X
08
0;
0#
b10100 5
b10100 :
b10100 R
b10100 W
07
b10100 9
0<
1)
b10100 2
b10100 ^
b10100 p
b10100 r
b0 6
b0 >
b0 H
b0 M
b0 3
b0 E
b0 P
b0 n
14
b10001 (
b10001 \
b10001 k
b0 G
b0 L
b0 Q
b10100 &
b10100 =
b10100 ]
b1 '
b1 D
b1 O
b1 Z
0F
bx ,
bx S
bx _
bx l
b10 A
b10 I
b11 @
b11 K
b11 N
b1 j
b10100 i
b1010000000010000010000011 +
b1010000000010000010000011 U
b1010000000010000010000011 o
b1000 /
b1000 `
b1000 c
b1000 0
b1000 [
b1000 b
b1000 g
b11000 $
b11000 a
b11000 s
b100 .
b100 V
b100 d
b100 e
b100 q
1!
#20
0!
#25
b11 (
b11 \
b11 k
b11 *
b11 T
b11 X
1#
b0 5
b0 :
b0 R
b0 W
b0 9
b0 &
b0 =
b0 ]
b0 2
b0 ^
b0 p
b0 r
b0 ,
b0 S
b0 _
b0 l
b11 j
b0 i
b10000110000011 +
b10000110000011 U
b10000110000011 o
b1100 /
b1100 `
b1100 c
b1100 0
b1100 [
b1100 b
b1100 g
b1000 $
b1000 a
b1000 s
b1000 .
b1000 V
b1000 d
b1000 e
b1000 q
1!
#30
0!
#35
bx *
bx T
bx X
0#
0)
b111001 5
b111001 :
b111001 R
b111001 W
b111001 9
b101000 &
b101000 =
b101000 ]
b111001 (
b111001 \
b111001 k
b101000 2
b101000 ^
b101000 p
b101000 r
b1 3
b1 E
b1 P
b1 n
11
b0 '
b0 D
b0 O
b0 Z
b11 ,
b11 S
b11 _
b11 l
b10001 -
b10001 ?
b10001 m
b1 B
b1 J
b100011 @
b100011 K
b100011 N
b1000 j
b11 i
b1 h
b10001100001010010000100011 +
b10001100001010010000100011 U
b10001100001010010000100011 o
b10000 /
b10000 `
b10000 c
b10000 0
b10000 [
b10000 b
b10000 g
b110100 $
b110100 a
b110100 s
b1100 .
b1100 V
b1100 d
b1100 e
b1100 q
1!
#40
0!
#45
b1 (
b1 \
b1 k
b1 5
b1 :
b1 R
b1 W
1)
b1 &
b1 =
b1 ]
b1 9
b1 2
b1 ^
b1 p
b1 r
b10 G
b10 L
b10 Q
b0 3
b0 E
b0 P
b0 n
01
b10001 ,
b10001 S
b10001 _
b10001 l
b0 -
b0 ?
b0 m
b0 B
b0 J
b0 A
b0 I
b10011 @
b10011 K
b10011 N
b0 j
b1 i
b0 h
b100000000000000010011 +
b100000000000000010011 U
b100000000000000010011 o
b111 *
b111 T
b111 X
b10100 /
b10100 `
b10100 c
b10100 0
b10100 [
b10100 b
b10100 g
b10001 $
b10001 a
b10001 s
b10000 .
b10000 V
b10000 d
b10000 e
b10000 q
1!
#50
0!
#55
x8
x;
x#
x7
b11 3
b11 E
b11 P
b11 n
x<
b11111111111111111111111111101100 &
b11111111111111111111111111101100 =
b11111111111111111111111111101100 ]
b10 '
b10 D
b10 O
b10 Z
b0 G
b0 L
b0 Q
1%
bx *
bx T
bx X
b11000 (
b11000 \
b11000 k
b11111111111111111111111111101100 2
b11111111111111111111111111101100 ^
b11111111111111111111111111101100 p
b11111111111111111111111111101100 r
1C
bx ,
bx S
bx _
bx l
bx 5
bx :
bx R
bx W
b1111111 B
b1111111 J
b111 A
b111 I
b1101111 @
b1101111 K
b1101111 N
b100 j
b1101 i
b11111 h
bx 9
b11111110110111111111001001101111 +
b11111110110111111111001001101111 U
b11111110110111111111001001101111 o
b0 /
b0 `
b0 c
bx -
bx ?
bx m
b11000 0
b11000 [
b11000 b
b11000 g
b0 $
b0 a
b0 s
b10100 .
b10100 V
b10100 d
b10100 e
b10100 q
1!
#60
0!
#65
bx *
bx T
bx X
08
1;
0#
b10100 &
b10100 =
b10100 ]
b1 6
b1 >
b1 H
b1 M
b11111111111111111111111111101101 5
b11111111111111111111111111101101 :
b11111111111111111111111111101101 R
b11111111111111111111111111101101 W
17
b11000 2
b11000 ^
b11000 p
b11000 r
b11111111111111111111111111101101 9
1<
0)
b10 3
b10 E
b10 P
b10 n
04
b0 '
b0 D
b0 O
b0 Z
b1 G
b1 L
b1 Q
0%
1F
0C
b10100 ,
b10100 S
b10100 _
b10100 l
b1 -
b1 ?
b1 m
b11111111111111111111111111101101 (
b11111111111111111111111111101101 \
b11111111111111111111111111101101 k
b0 B
b0 J
b0 A
b0 I
b1100011 @
b1100011 K
b1100011 N
b11000 j
b10 i
b0 h
b1000000000110001100011 +
b1000000000110001100011 U
b1000000000110001100011 o
b100 /
b100 `
b100 c
b100 0
b100 [
b100 b
b100 g
b11000 $
b11000 a
b11000 s
b0 .
b0 V
b0 d
b0 e
b0 q
1!
#70
0!
#75
b1101 *
b1101 T
b1101 X
08
0;
0#
b10101 5
b10101 :
b10101 R
b10101 W
07
b10101 9
0<
1)
b10100 2
b10100 ^
b10100 p
b10100 r
b0 6
b0 >
b0 H
b0 M
b0 3
b0 E
b0 P
b0 n
14
b1101 (
b1101 \
b1101 k
b0 G
b0 L
b0 Q
b10100 &
b10100 =
b10100 ]
b1 '
b1 D
b1 O
b1 Z
0F
bx ,
bx S
bx _
bx l
b10 A
b10 I
b11 @
b11 K
b11 N
b1 j
b10100 i
b1010000000010000010000011 +
b1010000000010000010000011 U
b1010000000010000010000011 o
b1000 /
b1000 `
b1000 c
b1000 0
b1000 [
b1000 b
b1000 g
b11000 $
b11000 a
b11000 s
b100 .
b100 V
b100 d
b100 e
b100 q
1!
#80
0!
#85
b111 (
b111 \
b111 k
b111 *
b111 T
b111 X
b1 5
b1 :
b1 R
b1 W
b1 9
b0 &
b0 =
b0 ]
b0 2
b0 ^
b0 p
b0 r
b1 ,
b1 S
b1 _
b1 l
b11 j
b0 i
b10000110000011 +
b10000110000011 U
b10000110000011 o
b1100 /
b1100 `
b1100 c
b1100 0
b1100 [
b1100 b
b1100 g
b1000 $
b1000 a
b1000 s
b1000 .
b1000 V
b1000 d
b1000 e
b1000 q
1!
#90
0!
#95
bx *
bx T
bx X
0)
b110101 5
b110101 :
b110101 R
b110101 W
b110101 9
b101000 &
b101000 =
b101000 ]
b110101 (
b110101 \
b110101 k
b101000 2
b101000 ^
b101000 p
b101000 r
b1 3
b1 E
b1 P
b1 n
11
b0 '
b0 D
b0 O
b0 Z
b111 ,
b111 S
b111 _
b111 l
b1101 -
b1101 ?
b1101 m
b1 B
b1 J
b100011 @
b100011 K
b100011 N
b1000 j
b11 i
b1 h
b10001100001010010000100011 +
b10001100001010010000100011 U
b10001100001010010000100011 o
b10000 /
b10000 `
b10000 c
b10000 0
b10000 [
b10000 b
b10000 g
b110100 $
b110100 a
b110100 s
b1100 .
b1100 V
b1100 d
b1100 e
b1100 q
1!
#100
0!
#105
b10 (
b10 \
b10 k
b10 5
b10 :
b10 R
b10 W
1)
b1 &
b1 =
b1 ]
b10 9
b1 2
b1 ^
b1 p
b1 r
b10 G
b10 L
b10 Q
b0 3
b0 E
b0 P
b0 n
01
b1101 ,
b1101 S
b1101 _
b1101 l
b1 -
b1 ?
b1 m
b0 B
b0 J
b0 A
b0 I
b10011 @
b10011 K
b10011 N
b0 j
b1 i
b0 h
b100000000000000010011 +
b100000000000000010011 U
b100000000000000010011 o
b10 *
b10 T
b10 X
b10100 /
b10100 `
b10100 c
b10100 0
b10100 [
b10100 b
b10100 g
b10001 $
b10001 a
b10001 s
b10000 .
b10000 V
b10000 d
b10000 e
b10000 q
1!
#110
0!
#115
x8
x;
x#
x7
b11 3
b11 E
b11 P
b11 n
x<
b11111111111111111111111111101100 &
b11111111111111111111111111101100 =
b11111111111111111111111111101100 ]
b10 '
b10 D
b10 O
b10 Z
b0 G
b0 L
b0 Q
1%
bx *
bx T
bx X
b11000 (
b11000 \
b11000 k
b11111111111111111111111111101100 2
b11111111111111111111111111101100 ^
b11111111111111111111111111101100 p
b11111111111111111111111111101100 r
1C
bx ,
bx S
bx _
bx l
bx 5
bx :
bx R
bx W
b1111111 B
b1111111 J
b111 A
b111 I
b1101111 @
b1101111 K
b1101111 N
b100 j
b1101 i
b11111 h
bx 9
b11111110110111111111001001101111 +
b11111110110111111111001001101111 U
b11111110110111111111001001101111 o
b0 /
b0 `
b0 c
bx -
bx ?
bx m
b11000 0
b11000 [
b11000 b
b11000 g
b0 $
b0 a
b0 s
b10100 .
b10100 V
b10100 d
b10100 e
b10100 q
1!
#120
0!
#125
bx *
bx T
bx X
08
1;
0#
b10100 &
b10100 =
b10100 ]
b1 6
b1 >
b1 H
b1 M
b11111111111111111111111111101110 5
b11111111111111111111111111101110 :
b11111111111111111111111111101110 R
b11111111111111111111111111101110 W
17
b11000 2
b11000 ^
b11000 p
b11000 r
b11111111111111111111111111101110 9
1<
0)
b10 3
b10 E
b10 P
b10 n
04
b0 '
b0 D
b0 O
b0 Z
b1 G
b1 L
b1 Q
0%
1F
0C
b10100 ,
b10100 S
b10100 _
b10100 l
b10 -
b10 ?
b10 m
b11111111111111111111111111101110 (
b11111111111111111111111111101110 \
b11111111111111111111111111101110 k
b0 B
b0 J
b0 A
b0 I
b1100011 @
b1100011 K
b1100011 N
b11000 j
b10 i
b0 h
b1000000000110001100011 +
b1000000000110001100011 U
b1000000000110001100011 o
b100 /
b100 `
b100 c
b100 0
b100 [
b100 b
b100 g
b11000 $
b11000 a
b11000 s
b0 .
b0 V
b0 d
b0 e
b0 q
1!
#130
0!
#135
b10010 *
b10010 T
b10010 X
08
0;
0#
b10110 5
b10110 :
b10110 R
b10110 W
07
b10110 9
0<
1)
b10100 2
b10100 ^
b10100 p
b10100 r
b0 6
b0 >
b0 H
b0 M
b0 3
b0 E
b0 P
b0 n
14
b10010 (
b10010 \
b10010 k
b0 G
b0 L
b0 Q
b10100 &
b10100 =
b10100 ]
b1 '
b1 D
b1 O
b1 Z
0F
bx ,
bx S
bx _
bx l
b10 A
b10 I
b11 @
b11 K
b11 N
b1 j
b10100 i
b1010000000010000010000011 +
b1010000000010000010000011 U
b1010000000010000010000011 o
b1000 /
b1000 `
b1000 c
b1000 0
b1000 [
b1000 b
b1000 g
b11000 $
b11000 a
b11000 s
b100 .
b100 V
b100 d
b100 e
b100 q
1!
#140
0!
#145
b10 (
b10 \
b10 k
b10 *
b10 T
b10 X
b10 5
b10 :
b10 R
b10 W
b10 9
b0 &
b0 =
b0 ]
b0 2
b0 ^
b0 p
b0 r
b10 ,
b10 S
b10 _
b10 l
b11 j
b0 i
b10000110000011 +
b10000110000011 U
b10000110000011 o
b1100 /
b1100 `
b1100 c
b1100 0
b1100 [
b1100 b
b1100 g
b1000 $
b1000 a
b1000 s
b1000 .
b1000 V
b1000 d
b1000 e
b1000 q
1!
#150
0!
#155
bx *
bx T
bx X
b111010 (
b111010 \
b111010 k
0)
b111010 5
b111010 :
b111010 R
b111010 W
b111010 9
b101000 &
b101000 =
b101000 ]
b101000 2
b101000 ^
b101000 p
b101000 r
b1 3
b1 E
b1 P
b1 n
11
b0 '
b0 D
b0 O
b0 Z
b10010 -
b10010 ?
b10010 m
b1 B
b1 J
b100011 @
b100011 K
b100011 N
b1000 j
b11 i
b1 h
b10001100001010010000100011 +
b10001100001010010000100011 U
b10001100001010010000100011 o
b10000 /
b10000 `
b10000 c
b10000 0
b10000 [
b10000 b
b10000 g
b110100 $
b110100 a
b110100 s
b1100 .
b1100 V
b1100 d
b1100 e
b1100 q
1!
#160
0!
#165
b11 (
b11 \
b11 k
b11 5
b11 :
b11 R
b11 W
1)
b1 &
b1 =
b1 ]
b11 9
b1 2
b1 ^
b1 p
b1 r
b10 G
b10 L
b10 Q
b0 3
b0 E
b0 P
b0 n
01
b10010 ,
b10010 S
b10010 _
b10010 l
b10 -
b10 ?
b10 m
b0 B
b0 J
b0 A
b0 I
b10011 @
b10011 K
b10011 N
b0 j
b1 i
b0 h
b100000000000000010011 +
b100000000000000010011 U
b100000000000000010011 o
b110 *
b110 T
b110 X
b10100 /
b10100 `
b10100 c
b10100 0
b10100 [
b10100 b
b10100 g
b10001 $
b10001 a
b10001 s
b10000 .
b10000 V
b10000 d
b10000 e
b10000 q
1!
#170
0!
